README.md
setup.py
blockchainetl/__init__.py
blockchainetl/atomic_counter.py
blockchainetl/csv_utils.py
blockchainetl/exporters.py
blockchainetl/file_utils.py
blockchainetl/logging_utils.py
blockchainetl/jobs/__init__.py
blockchainetl/jobs/base_job.py
blockchainetl/jobs/exporters/__init__.py
blockchainetl/jobs/exporters/composite_item_exporter.py
blockchainetl/jobs/exporters/console_item_exporter.py
blockchainetl/jobs/exporters/google_pubsub_item_exporter.py
blockchainetl/jobs/exporters/in_memory_item_exporter.py
blockchainetl/jobs/exporters/postgres_item_exporter.py
blockchainetl/streaming/__init__.py
blockchainetl/streaming/postgres_utils.py
blockchainetl/streaming/streamer.py
blockchainetl/streaming/streamer_adapter_stub.py
blockchainetl/streaming/streaming_utils.py
ethereumetl/__init__.py
ethereumetl/__main__.py
ethereumetl/atomic_counter.py
ethereumetl/csv_utils.py
ethereumetl/erc20_abi.py
ethereumetl/exporters.py
ethereumetl/json_rpc_requests.py
ethereumetl/mainnet_daofork_state_changes.py
ethereumetl/mainnet_genesis_alloc.py
ethereumetl/misc_utils.py
ethereumetl/progress_logger.py
ethereumetl/thread_local_proxy.py
ethereumetl/utils.py
ethereumetl/cli/__init__.py
ethereumetl/cli/export_all.py
ethereumetl/cli/export_blocks_and_transactions.py
ethereumetl/cli/export_contracts.py
ethereumetl/cli/export_geth_traces.py
ethereumetl/cli/export_origin.py
ethereumetl/cli/export_receipts_and_logs.py
ethereumetl/cli/export_token_transfers.py
ethereumetl/cli/export_tokens.py
ethereumetl/cli/export_traces.py
ethereumetl/cli/extract_contracts.py
ethereumetl/cli/extract_csv_column.py
ethereumetl/cli/extract_field.py
ethereumetl/cli/extract_geth_traces.py
ethereumetl/cli/extract_token_transfers.py
ethereumetl/cli/extract_tokens.py
ethereumetl/cli/filter_items.py
ethereumetl/cli/get_block_range_for_date.py
ethereumetl/cli/get_block_range_for_timestamps.py
ethereumetl/cli/get_keccak_hash.py
ethereumetl/cli/stream.py
ethereumetl/domain/__init__.py
ethereumetl/domain/block.py
loom_etl.egg-info/PKG-INFO
loom_etl.egg-info/SOURCES.txt
loom_etl.egg-info/dependency_links.txt
loom_etl.egg-info/entry_points.txt
loom_etl.egg-info/requires.txt
loom_etl.egg-info/top_level.txt
