Metadata-Version: 2.1
Name: loom-etl
Version: 1.5.1
Summary: Tools for exporting Loom blockchain data to CSV or JSON
Home-page: UNKNOWN
Author: Jetson Lim
Author-email: jettson.lim@gmail.com
License: UNKNOWN
Keywords: loom
Platform: UNKNOWN
Classifier: Development Status :: 5 - Production/Stable
Classifier: Intended Audience :: Developers
Classifier: License :: OSI Approved :: MIT License
Classifier: Programming Language :: Python :: 3
Classifier: Programming Language :: Python :: 3.5
Classifier: Programming Language :: Python :: 3.6
Classifier: Programming Language :: Python :: 3.7
Requires-Python: >=3.5.3,<3.8.0
Provides-Extra: streaming
Provides-Extra: dev
